efictopub/__init__.py
efictopub/__main__.py
efictopub/archive.py
efictopub/config.py
efictopub/cover_generator.py
efictopub/efictopub.py
efictopub/epub_writer.py
efictopub/exceptions.py
efictopub/git.py
efictopub/html_parser.py
efictopub/cli/__init__.py
efictopub/cli/cli.py
efictopub/cli/opts.py
efictopub/fetchers/__init__.py
efictopub/fetchers/ao3.py
efictopub/fetchers/archive.py
efictopub/fetchers/base_fetcher.py
efictopub/fetchers/ffnet.py
efictopub/fetchers/reddit_author.py
efictopub/fetchers/reddit_next.py
efictopub/fetchers/reddit_wiki_page.py
efictopub/fetchers/royalroad.py
efictopub/fetchers/spacebattles.py
efictopub/fetchers/wordpress.py
efictopub/lib/__init__.py
efictopub/lib/comment_pruner.py
efictopub/lib/reddit_util.py
efictopub/lib/request_dispatcher.py
efictopub/models/__init__.py
efictopub/models/chapter.py
efictopub/models/comment.py
efictopub/models/story.py
efictopub/models/ffnet/__init__.py
efictopub/models/ffnet/ffnet_chapter.py
efictopub/models/ffnet/ffnet_review.py
efictopub/models/ffnet/ffnet_reviews.py
efictopub/models/reddit/__init__.py
efictopub/models/reddit/reddit_comment.py
efictopub/models/reddit/reddit_submission.py
efictopub/models/reddit/reddit_wiki_page.py
efictopub/models/spacebattles/__init__.py
efictopub/models/spacebattles/spacebattles_post.py
efictopub/models/wordpress/__init__.py
efictopub/models/wordpress/wordpress_comment.py
efictopub/models/wordpress/wordpress_entry.py
efictopub-0.0.0.dist-info/LICENSE
efictopub-0.0.0.dist-info/METADATA
efictopub-0.0.0.dist-info/WHEEL
efictopub-0.0.0.dist-info/entry_points.txt
efictopub-0.0.0.dist-info/top_level.txt
efictopub-0.0.0.dist-info/RECORD
